MANIFEST.in
README
setup.cfg
setup.py
ewsclient/__init__.py
ewsclient/monkey.py
ewsclient/xml.xsd
ewsclient.egg-info/PKG-INFO
ewsclient.egg-info/SOURCES.txt
ewsclient.egg-info/dependency_links.txt
ewsclient.egg-info/entry_points.txt
ewsclient.egg-info/not-zip-safe
ewsclient.egg-info/requires.txt
ewsclient.egg-info/top_level.txt