Metadata-Version: 1.0
Name: ewsclient
Version: 0.3.1
Summary: Client for Microsoft Exchange Web Services
Home-page: http://bitbucket.org/dholth/ewsclient
Author: Daniel Holth
Author-email: dholth@gmail.com
License: LGPL
Platform: UNKNOWN
